setup.py
nadera/__init__.py
nadera/backbone.py
nadera/eval_class_v63.py
nadera/main.py
nadera/nadera_class_v63.py
nadera/yolact.py
nadera.egg-info/PKG-INFO
nadera.egg-info/SOURCES.txt
nadera.egg-info/dependency_links.txt
nadera.egg-info/requires.txt
nadera.egg-info/top_level.txt
nadera/data/__init__.py
nadera/data/coco.py
nadera/data/config.py
nadera/layers/__init__.py
nadera/layers/box_utils.py
nadera/layers/interpolate.py
nadera/layers/output_utils.py
nadera/layers/functions/__init__.py
nadera/layers/functions/detection.py
nadera/layers/modules/__init__.py
nadera/layers/modules/multibox_loss.py
nadera/utils/__init__.py
nadera/utils/augmentations.py
nadera/utils/cython_nms.pyx
nadera/utils/functions.py
nadera/utils/timer.py
nadera/weights2/emes.png
nadera/weights2/nadera_model_v6.3.json
nadera/weights2/nadera_weight_v6.3.h5